confing-0.1.4.dist-info/METADATA
confing-0.1.4.dist-info/DESCRIPTION.rst
confing-0.1.4.dist-info/RECORD
confing-0.1.4.dist-info/metadata.json
confing-0.1.4.dist-info/top_level.txt
confing-0.1.4.dist-info/WHEEL
confing/__init__.py
confing/confing.py
confing/data.py
