Metadata-Version: 2.0
Name: confing
Version: 0.1.4
Summary: Described configuration for large, complex projects
Home-page: https://github.com/fahhem/confing
Author: Fahrzin Hemmati
Author-email: fahhem@chainreactionmfg.com
License: Apache 2.0
Keywords: confing development
Platform: UNKNOWN
Classifier: Development Status :: 3 - Alpha
Classifier: Intended Audience :: Developers
Classifier: Topic :: Software Development
Classifier: Topic :: Utilities
Classifier: License :: OSI Approved :: Apache Software License
Classifier: Programming Language :: Python :: 3
Requires-Dist: colander (==1.0)
Requires-Dist: setuptools
